delayedKeyInt/__init__.py
delayedKeyInt-0.0.1.dist-info/LICENSE
delayedKeyInt-0.0.1.dist-info/METADATA
delayedKeyInt-0.0.1.dist-info/WHEEL
delayedKeyInt-0.0.1.dist-info/top_level.txt
delayedKeyInt-0.0.1.dist-info/RECORD
